hid_parser/__init__.py
hid_parser/data.py
hid_parser-0.1.0.dist-info/licenses/LICENSE
hid_parser-0.1.0.dist-info/WHEEL
hid_parser-0.1.0.dist-info/METADATA
hid_parser-0.1.0.dist-info/RECORD
