Metadata-Version: 2.4
Name: hid-parser
Version: 0.1.0
Summary: Typed pure Python library to parse HID report descriptors
Author-email: Filipe Laíns <lains@riseup.net>
Requires-Python: >= 3.9
Classifier: License :: OSI Approved :: MIT License
Classifier: Programming Language :: Python :: 3
Classifier: Programming Language :: Python :: 3 :: Only
Classifier: Programming Language :: Python :: 3.9
Classifier: Programming Language :: Python :: 3.10
Classifier: Programming Language :: Python :: 3.11
Classifier: Programming Language :: Python :: 3.12
Classifier: Programming Language :: Python :: 3.13
Classifier: Programming Language :: Python :: 3.14
Classifier: Programming Language :: Python :: Implementation :: CPython
Classifier: Programming Language :: Python :: Implementation :: PyPy
License-File: LICENSE
Requires-Dist: typing_extensions >= 4.4.0; python_version < "3.13"
Project-URL: homepage, https://github.com/usb-tools/python-hid-parser
Project-URL: issues, https://github.com/usb-tools/python-hid-parser/issues
Project-URL: source, https://github.com/usb-tools/python-hid-parser
